{
    "ip": "89.138.248.233",
    "network": "89.138.240.0/20",
    "version": "IPv4",
    "city": "Kfar Saba",
    "region": "Central District",
    "region_code": "M",
    "country": "IL",
    "country_name": "Israel",
    "country_code": "IL",
    "country_code_iso3": "ISR",
    "country_capital": "Jerusalem",
    "country_tld": ".il",
    "continent_code": "AS",
    "in_eu": false,
    "postal": null,
    "latitude": 32.1772,
    "longitude": 34.9039,
    "timezone": "Asia/Jerusalem",
    "utc_offset": "+0200",
    "country_calling_code": "+972",
    "currency": "ILS",
    "currency_name": "Shekel",
    "languages": "he,ar-IL,en-IL,",
    "country_area": 20770.0,
    "country_population": 8883800,
    "asn": "AS1680",
    "org": "Cellcom Fixed Line Communication L.P"
}